{
   "id": 25048802,
   "token_id": "1482",
   "num_sales": 1,
   "background_color": null,
   "image_url": "https://lh3.googleusercontent.com/XNYtVQh12paHBMRWQp52oxokEeDXM30hvPmHDPPqGY4tfCCGyAIp78WBD2vxh2NjXZNcJjFlzJ5f-yDK5B5M94RlLwemqrQ5Hg0dZw",
   "image_preview_url": "https://lh3.googleusercontent.com/XNYtVQh12paHBMRWQp52oxokEeDXM30hvPmHDPPqGY4tfCCGyAIp78WBD2vxh2NjXZNcJjFlzJ5f-yDK5B5M94RlLwemqrQ5Hg0dZw=s250",
   "image_thumbnail_url": "https://lh3.googleusercontent.com/XNYtVQh12paHBMRWQp52oxokEeDXM30hvPmHDPPqGY4tfCCGyAIp78WBD2vxh2NjXZNcJjFlzJ5f-yDK5B5M94RlLwemqrQ5Hg0dZw=s128",
   "image_original_url": "https://ipfs.io/ipfs/QmVoqz2N3SkWhx1xLYgc5QuanfskZFwpZUeLvZAJi5xXwZ",
   "animation_url": null,
   "animation_original_url": null,
   "name": "CyberKong #1482",
   "description": null,
   "external_link": "https://www.cyberkongz.com/kong/1482",
   "asset_contract": {
      "address": "0x57a204aa1042f6e66dd7730813f4024114d74f37",
      "asset_contract_type": "non-fungible",
      "created_date": "2021-04-16T19:57:15.011015",
      "name": "CyberKongz",
      "nft_version": "3.0",
      "opensea_version": null,
      "owner": 53953400,
      "schema_name": "ERC721",
      "symbol": "KONGZ",
      "total_supply": "3",
      "description": "Welcome to an alternate reality, where evolution took a different route and weird apes roam the earth.\r\nSome appear normal. Some look weird. And some are just damn cool! \r\nEvery CyberKong is unique and owns randomized items with different rarities. A few are super rare and even animated!\r\n**Maybe some of them look familiar!**",
      "external_link": "http://cyberkongz.com",
      "image_url": "https://lh3.googleusercontent.com/LIpf9z6Ux8uxn69auBME9FCTXpXqSYFo8ZLO1GaM8T7S3hiKScHaClXe0ZdhTv5br6FE2g5i-J5SobhKFsYfe6CIMCv-UfnrlYFWOM4=s120",
      "default_to_fiat": false,
      "dev_buyer_fee_basis_points": 0,
      "dev_seller_fee_basis_points": 250,
      "only_proxied_transfers": false,
      "opensea_buyer_fee_basis_points": 0,
      "opensea_seller_fee_basis_points": 250,
      "buyer_fee_basis_points": 0,
      "seller_fee_basis_points": 500,
      "payout_address": "0xeef61546a3e2ffe36cf7d9c826c76edcb0dc6e22"
   },
   "permalink": "https://opensea.io/assets/0x57a204aa1042f6e66dd7730813f4024114d74f37/1482",
   "collection": {
      "banner_image_url": "https://lh3.googleusercontent.com/8QAOgrzgfu8tR0K80iZW_93o9dUpyGMACpwr4kSeTvinu2hYBvzMOyLoHspo6IPpz7G2Xe57VTXfgGPECzWTaH_oYFNVCuA12AIDJA=s2500",
      "chat_url": null,
      "created_date": "2021-04-16T19:57:15.677123",
      "default_to_fiat": false,
      "description": "Welcome to an alternate reality, where evolution took a different route and weird apes roam the earth.\r\nSome appear normal. Some look weird. And some are just damn cool! \r\nEvery CyberKong is unique and owns randomized items with different rarities. A few are super rare and even animated!\r\n**Maybe some of them look familiar!**",
      "dev_buyer_fee_basis_points": "0",
      "dev_seller_fee_basis_points": "250",
      "discord_url": "https://discord.gg/cyberkongz",
      "display_data": {
         "card_display_style": "cover"
      },
      "external_url": "http://cyberkongz.com",
      "featured": false,
      "featured_image_url": "https://lh3.googleusercontent.com/CCV8it28JK9YoZ4lFLnfnc1wqeYP4h6_tHHPSj-9jqMTeQSz_f2M79eopKYE7M__unKE5_4YU3td1VkKKPjHyoH5i3KIxtalWHR8=s300",
      "hidden": false,
      "safelist_request_status": "verified",
      "image_url": "https://lh3.googleusercontent.com/LIpf9z6Ux8uxn69auBME9FCTXpXqSYFo8ZLO1GaM8T7S3hiKScHaClXe0ZdhTv5br6FE2g5i-J5SobhKFsYfe6CIMCv-UfnrlYFWOM4=s120",
      "is_subject_to_whitelist": false,
      "large_image_url": "https://lh3.googleusercontent.com/CCV8it28JK9YoZ4lFLnfnc1wqeYP4h6_tHHPSj-9jqMTeQSz_f2M79eopKYE7M__unKE5_4YU3td1VkKKPjHyoH5i3KIxtalWHR8=s300",
      "medium_username": "cyberkongz",
      "name": "CyberKongz",
      "only_proxied_transfers": false,
      "opensea_buyer_fee_basis_points": "0",
      "opensea_seller_fee_basis_points": "250",
      "payout_address": "0xeef61546a3e2ffe36cf7d9c826c76edcb0dc6e22",
      "require_email": false,
      "short_description": null,
      "slug": "cyberkongz",
      "telegram_url": null,
      "twitter_username": "CyberKongz",
      "instagram_username": null,
      "wiki_url": null
   },
   "decimals": 0,
   "token_metadata": "https://kongz.herokuapp.com/api/metadata/1482",
   "owner": {
      "user": {
         "username": "Q127500"
      },
      "profile_img_url": "https://storage.googleapis.com/opensea-static/opensea-profile/1.png",
      "address": "0x191ef0546034e660ce94deb78f54bc82cf8bff17",
      "config": ""
   },
   "sell_orders": [
      {
         "created_date": "2022-01-18T17:45:00.672220",
         "closing_date": "2022-02-18T17:44:22",
         "closing_extendable": false,
         "expiration_time": 1645206262,
         "listing_time": 1642527771,
         "order_hash": "0xbef1a67f1aeb21c33e336a7efdddc204ea9bfc1206e22751adb33ed9544b49cc",
         "metadata": {
            "asset": {
               "id": "1482",
               "address": "0x57a204aa1042f6e66dd7730813f4024114d74f37"
            },
            "schema": "ERC721"
         },
         "exchange": "0x7be8076f4ea4a4ad08075c2508e481d6c946d12b",
         "maker": {
            "user": 3932455,
            "profile_img_url": "https://storage.googleapis.com/opensea-static/opensea-profile/1.png",
            "address": "0x191ef0546034e660ce94deb78f54bc82cf8bff17",
            "config": ""
         },
         "taker": {
            "user": 1766,
            "profile_img_url": "https://storage.googleapis.com/opensea-static/opensea-profile/1.png",
            "address": "0x0000000000000000000000000000000000000000",
            "config": ""
         },
         "current_price": "23000000000000000000.00000000",
         "current_bounty": "230000000000000000",
         "bounty_multiple": "0.01",
         "maker_relayer_fee": "500",
         "taker_relayer_fee": "0",
         "maker_protocol_fee": "0",
         "taker_protocol_fee": "0",
         "maker_referrer_fee": "0",
         "fee_recipient": {
            "user": 3585,
            "profile_img_url": "https://storage.googleapis.com/opensea-static/opensea-profile/28.png",
            "address": "0x5b3256965e7c3cf26e11fcaf296dfc8807c01073",
            "config": "verified"
         },
         "fee_method": 1,
         "side": 1,
         "sale_kind": 0,
         "target": "0x57a204aa1042f6e66dd7730813f4024114d74f37",
         "how_to_call": 0,
         "calldata": "0x23b872dd000000000000000000000000191ef0546034e660ce94deb78f54bc82cf8bff17000000000000000000000000000000000000000000000000000000000000000000000000000000000000000000000000000000000000000000000000000005ca",
         "replacement_pattern": "0x000000000000000000000000000000000000000000000000000000000000000000000000ffffffffffffffffffffffffffffffffffffffffffffffffffffffffffffffff0000000000000000000000000000000000000000000000000000000000000000",
         "static_target": "0x0000000000000000000000000000000000000000",
         "static_extradata": "0x",
         "payment_token": "0x0000000000000000000000000000000000000000",
         "payment_token_contract": {
            "id": 1,
            "symbol": "ETH",
            "address": "0x0000000000000000000000000000000000000000",
            "image_url": "https://storage.opensea.io/files/6f8e2979d428180222796ff4a33ab929.svg",
            "name": "Ether",
            "decimals": 18,
            "eth_price": "1.000000000000000",
            "usd_price": "3125.869999999999891000"
         },
         "base_price": "23000000000000000000",
         "extra": "0",
         "quantity": "1",
         "salt": "60905481865228507130999481842732280087069409730223692140373546610510961562004",
         "v": 27,
         "r": "0x942dbe0eebe6a5f26d1aafc5a38f953a8b84549c001184dc8a46dabf0f691608",
         "s": "0x6aea9873ac97834c1b5bfd02bc5af4dc6895e2882b8da5cbc8cc1156b324e2f0",
         "approved_on_chain": false,
         "cancelled": false,
         "finalized": false,
         "marked_invalid": false,
         "prefixed_hash": "0x6452bf2ea480bb83a9c2271f3d5d81d0662da8228ee7963cbb7675d172a0732a"
      }
   ],
   "creator": {
      "user": {
         "username": null
      },
      "profile_img_url": "https://storage.googleapis.com/opensea-static/opensea-profile/27.png",
      "address": "0x000000048797808be86aa9786c1f402671192d6b",
      "config": ""
   },
   "traits": [
      {
         "trait_type": "Baby Trait",
         "value": "Pink Pacifier",
         "display_type": null,
         "max_value": null,
         "trait_count": 236,
         "order": null
      },
      {
         "trait_type": "birthday",
         "value": 1621073447.0,
         "display_type": "date",
         "max_value": null,
         "trait_count": 0,
         "order": null
      },
      {
         "trait_type": "Baby Trait",
         "value": "Blue Beanie",
         "display_type": null,
         "max_value": null,
         "trait_count": 214,
         "order": null
      },
      {
         "trait_type": "Baby Trait",
         "value": "Blue Bib",
         "display_type": null,
         "max_value": null,
         "trait_count": 306,
         "order": null
      },
      {
         "trait_type": "Type",
         "value": "Baby",
         "display_type": null,
         "max_value": null,
         "trait_count": 3712,
         "order": null
      }
   ],
   "last_sale": {
      "asset": {
         "token_id": "1482",
         "decimals": 0
      },
      "asset_bundle": null,
      "event_type": "successful",
      "event_timestamp": "2021-09-02T14:01:42",
      "auction_type": null,
      "total_price": "2380000000000000000",
      "payment_token": {
         "id": 1,
         "symbol": "ETH",
         "address": "0x0000000000000000000000000000000000000000",
         "image_url": "https://storage.opensea.io/files/6f8e2979d428180222796ff4a33ab929.svg",
         "name": "Ether",
         "decimals": 18,
         "eth_price": "1.000000000000000",
         "usd_price": "3125.869999999999891000"
      },
      "transaction": {
         "block_hash": "0x1b175beb8bdb8cab9ed4646ac010f6dc13ea8d4de804d36afdb5a59c6a974856",
         "block_number": "13146683",
         "from_account": {
            "user": {
               "username": "Degen66866"
            },
            "profile_img_url": "https://storage.googleapis.com/opensea-static/opensea-profile/12.png",
            "address": "0x14c639a0506337e0c0bbfe63c7e0a4520305e155",
            "config": ""
         },
         "id": 157657497,
         "timestamp": "2021-09-02T14:01:42",
         "to_account": {
            "user": {
               "username": "OpenSea-Orders"
            },
            "profile_img_url": "https://storage.googleapis.com/opensea-static/opensea-profile/22.png",
            "address": "0x7be8076f4ea4a4ad08075c2508e481d6c946d12b",
            "config": "verified"
         },
         "transaction_hash": "0x209feadd2b6a91dd3edc5f38a148c1693f841a4b985e51924656455673605221",
         "transaction_index": "318"
      },
      "created_date": "2021-09-02T14:02:13.860935",
      "quantity": "1"
   },
   "top_bid": null,
   "listing_date": null,
   "is_presale": false,
   "transfer_fee_payment_token": null,
   "transfer_fee": null
}